CHANGES.rst
CONTRIBUTORS.rst
MANIFEST.in
README.rst
TODO.txt
buildout.cfg
development.cfg
requirements.txt
setup.cfg
setup.py
docs/LICENSE.GPL
docs/LICENSE.txt
src/collective/__init__.py
src/collective.workspace.egg-info/PKG-INFO
src/collective.workspace.egg-info/SOURCES.txt
src/collective.workspace.egg-info/dependency_links.txt
src/collective.workspace.egg-info/entry_points.txt
src/collective.workspace.egg-info/namespace_packages.txt
src/collective.workspace.egg-info/not-zip-safe
src/collective.workspace.egg-info/requires.txt
src/collective.workspace.egg-info/top_level.txt
src/collective/workspace/__init__.py
src/collective/workspace/_compat.py
src/collective/workspace/adapters.py
src/collective/workspace/browser.py
src/collective/workspace/catalog.py
src/collective/workspace/configure.zcml
src/collective/workspace/events.py
src/collective/workspace/i18n.sh
src/collective/workspace/interfaces.py
src/collective/workspace/membership.py
src/collective/workspace/pas.py
src/collective/workspace/setuphandlers.py
src/collective/workspace/testing.py
src/collective/workspace/vocabs.py
src/collective/workspace/workspace.py
src/collective/workspace/locales/collective.workspace.pot
src/collective/workspace/locales/manual-collective.workspace.pot
src/collective/workspace/locales/manual-plone.pot
src/collective/workspace/locales/plone.pot
src/collective/workspace/locales/de/LC_MESSAGES/collective.workspace.po
src/collective/workspace/locales/de/LC_MESSAGES/plone.po
src/collective/workspace/locales/fi/LC_MESSAGES/collective.workspace.po
src/collective/workspace/locales/fi/LC_MESSAGES/plone.po
src/collective/workspace/profiles/default/actions.xml
src/collective/workspace/profiles/default/catalog.xml
src/collective/workspace/profiles/default/collective.workspace.txt
src/collective/workspace/profiles/default/metadata.xml
src/collective/workspace/profiles/default/registry.xml
src/collective/workspace/profiles/default/rolemap.xml
src/collective/workspace/templates/WorkspaceGroupManagerForm.zpt
src/collective/workspace/templates/team_roster.pt
src/collective/workspace/templates/team_roster_row.pt
src/collective/workspace/tests/__init__.py
src/collective/workspace/tests/test_example.py
src/collective/workspace/tests/test_robot.py
src/collective/workspace/tests/test_upgrades.py
src/collective/workspace/tests/test_workspace.py
src/collective/workspace/tests/workspace.robot