Metadata-Version: 2.1
Name: collective.workspace
Version: 3.0.0
Summary: Provide 'membership' in specific areas of a Plone Site
Home-page: https://github.com/collective/collective.workspace
Author: David Glick
Author-email: 
License: gpl
Keywords: plone workspace collaboration
Platform: UNKNOWN
Classifier: Environment :: Web Environment
Classifier: Framework :: Plone
Classifier: Framework :: Plone :: Addon
Classifier: Framework :: Plone :: 5.1
Classifier: Framework :: Plone :: 5.2
Classifier: Operating System :: OS Independent
Classifier: Programming Language :: Python
Classifier: Programming Language :: Python :: 2.7
Classifier: Programming Language :: Python :: 3.6
Classifier: Programming Language :: Python :: 3.7
Classifier: Programming Language :: Python :: 3.8
Classifier: Topic :: Software Development :: Libraries :: Python Modules
Provides-Extra: develop
Provides-Extra: test
